Metadata-Version: 2.4
Name: cell2cell
Version: 0.8.2
Summary: TBD
Author: cell2cell development team
Author-email: earmingo@ucsd.edu
Maintainer: cell2cell development team
Maintainer-email: earmingol@eng.ucsd.edu
License: BSD-3-Clause
Classifier: Development Status :: 2 - Pre-Alpha
Classifier: License :: OSI Approved :: BSD License
Classifier: Topic :: Software Development :: Libraries
Classifier: Topic :: Scientific/Engineering
Classifier: Topic :: Scientific/Engineering :: Bio-Informatics
Classifier: Programming Language :: Python :: 3
Classifier: Programming Language :: Python :: 3 :: Only
Classifier: Operating System :: Unix
Classifier: Operating System :: POSIX
Classifier: Operating System :: MacOS :: MacOS X
License-File: LICENSE.txt
Requires-Dist: numpy>=1.16
Requires-Dist: pandas>=1.0.0
Requires-Dist: xlrd>=1.1
Requires-Dist: openpyxl>=2.6.2
Requires-Dist: networkx>=2.3
Requires-Dist: matplotlib>=3.2.0
Requires-Dist: seaborn>=0.11.0
Requires-Dist: scikit-learn
Requires-Dist: umap-learn
Requires-Dist: tqdm
Requires-Dist: statsmodels
Requires-Dist: statannotations
Requires-Dist: tensorly
Requires-Dist: kneed
Requires-Dist: scanpy
Requires-Dist: gseapy>=1.0.3
Dynamic: author
Dynamic: author-email
Dynamic: classifier
Dynamic: description
Dynamic: description-content-type
Dynamic: license
Dynamic: license-file
Dynamic: maintainer
Dynamic: maintainer-email
Dynamic: requires-dist
Dynamic: summary
